[
    {
        "title": "Hanuman 2024",
        "subtitle": "Teja Sajja",
        "url": "../src/assets/movies/upcoming/hanuman.jpg"
    },
    {
        "title": "Sihinayaki Adare",
        "subtitle": "Hemal Ranasinghe",
        "url": "../src/assets/movies/upcoming/sihinayaki-adare.jpeg"
    },
    {
        "title": "Pushpa 2",
        "subtitle": "Allu Arjun",
        "url": "../src/assets/movies/upcoming/pushpa2.jpg"
    },
    {
        "title": "Kungfu Panda 4",
        "subtitle": "Jack Black",
        "url": "../src/assets/movies/upcoming/kungfu-panda-4.jpg"
    },
    {
        "title": "Deadpool 3",
        "subtitle": "Ryan Reynolds",
        "url": "../src/assets/movies/upcoming/deadpool.jpg"
    }



]